{
  "info": {
    "_postman_id": "f5b66d4f-3701-4be5-a131-08149e6f1f46",
    "name": "TransitOps API Detailed",
    "description": "Comprehensive Postman collection for TransitOps API testing including Auth, Vehicle, Driver, and Trip Management.",
    "schema": "https://schema.getpostman.com/json/collection/v2.1.0/collection.json"
  },
  "item": [
    {
      "name": "Authentication",
      "item": [
        {
          "name": "1. Signup Admin (Success)",
          "event": [
            {
              "listen": "test",
              "script": {
                "exec": [
                  "pm.test(\"Status code is 200\", function () {",
                  "    pm.response.to.have.status(200);",
                  "});"
                ],
                "type": "text/javascript"
              }
            }
          ],
          "request": {
            "method": "POST",
            "header": [{"key": "Content-Type", "value": "application/json"}],
            "body": {
              "mode": "raw",
              "raw": "{\n  \"name\": \"Admin User\",\n  \"email\": \"admin@transitops.com\",\n  \"password\": \"password123\",\n  \"roles\": [\"admin\"]\n}"
            },
            "url": {
              "raw": "{{base_url}}/api/auth/signup",
              "host": ["{{base_url}}"],
              "path": ["api", "auth", "signup"]
            }
          },
          "response": []
        },
        {
          "name": "2. Signin Admin (Success)",
          "event": [
            {
              "listen": "test",
              "script": {
                "exec": [
                  "pm.test(\"Status code is 200\", function () {",
                  "    pm.response.to.have.status(200);",
                  "});",
                  "var jsonData = pm.response.json();",
                  "pm.environment.set(\"jwt_token\", jsonData.token);"
                ],
                "type": "text/javascript"
              }
            }
          ],
          "request": {
            "method": "POST",
            "header": [{"key": "Content-Type", "value": "application/json"}],
            "body": {
              "mode": "raw",
              "raw": "{\n  \"email\": \"admin@transitops.com\",\n  \"password\": \"password123\"\n}"
            },
            "url": {
              "raw": "{{base_url}}/api/auth/signin",
              "host": ["{{base_url}}"],
              "path": ["api", "auth", "signin"]
            }
          },
          "response": []
        }
      ]
    },
    {
      "name": "Vehicle Management",
      "item": [
        {
          "name": "3. Create Vehicle (Success)",
          "event": [
            {
              "listen": "test",
              "script": {
                "exec": [
                  "pm.test(\"Status code is 201\", function () {",
                  "    pm.response.to.have.status(201);",
                  "});",
                  "var jsonData = pm.response.json();",
                  "pm.environment.set(\"vehicle_id\", jsonData.id);"
                ],
                "type": "text/javascript"
              }
            }
          ],
          "request": {
            "auth": {"type": "bearer", "bearer": [{"key": "token", "value": "{{jwt_token}}", "type": "string"}]},
            "method": "POST",
            "header": [{"key": "Content-Type", "value": "application/json"}],
            "body": {
              "mode": "raw",
              "raw": "{\n  \"registrationNumber\": \"VAN-001\",\n  \"name\": \"Delivery Van 1\",\n  \"model\": \"Ford Transit\",\n  \"type\": \"VAN\",\n  \"maxLoadCapacity\": 1500.0,\n  \"odometerReading\": 12000.5,\n  \"acquisitionCost\": 45000.00\n}"
            },
            "url": {
              "raw": "{{base_url}}/api/v1/vehicles",
              "host": ["{{base_url}}"],
              "path": ["api", "v1", "vehicles"]
            }
          },
          "response": []
        }
      ]
    },
    {
      "name": "Driver Management",
      "item": [
        {
          "name": "4. Create Driver (Success)",
          "event": [
            {
              "listen": "test",
              "script": {
                "exec": [
                  "pm.test(\"Status code is 201\", function () {",
                  "    pm.response.to.have.status(201);",
                  "});",
                  "var jsonData = pm.response.json();",
                  "pm.environment.set(\"driver_id\", jsonData.id);"
                ],
                "type": "text/javascript"
              }
            }
          ],
          "request": {
            "auth": {"type": "bearer", "bearer": [{"key": "token", "value": "{{jwt_token}}", "type": "string"}]},
            "method": "POST",
            "header": [{"key": "Content-Type", "value": "application/json"}],
            "body": {
              "mode": "raw",
              "raw": "{\n  \"name\": \"Alex Johnson\",\n  \"licenseNumber\": \"LIC-987654321\",\n  \"licenseCategory\": \"Heavy\",\n  \"licenseExpiryDate\": \"2030-12-31\",\n  \"contactNumber\": \"+1-555-1234\",\n  \"safetyScore\": 100\n}"
            },
            "url": {
              "raw": "{{base_url}}/api/v1/drivers",
              "host": ["{{base_url}}"],
              "path": ["api", "v1", "drivers"]
            }
          },
          "response": []
        }
      ]
    },
    {
      "name": "Trip Management",
      "item": [
        {
          "name": "5. Create Trip (Success)",
          "event": [
            {
              "listen": "test",
              "script": {
                "exec": [
                  "pm.test(\"Status code is 201\", function () {",
                  "    pm.response.to.have.status(201);",
                  "});",
                  "var jsonData = pm.response.json();",
                  "pm.environment.set(\"trip_id\", jsonData.id);"
                ],
                "type": "text/javascript"
              }
            }
          ],
          "request": {
            "auth": {"type": "bearer", "bearer": [{"key": "token", "value": "{{jwt_token}}", "type": "string"}]},
            "method": "POST",
            "header": [{"key": "Content-Type", "value": "application/json"}],
            "body": {
              "mode": "raw",
              "raw": "{\n  \"source\": \"Warehouse A\",\n  \"destination\": \"Store B\",\n  \"vehicleId\": {{vehicle_id}},\n  \"driverId\": {{driver_id}},\n  \"cargoWeight\": 1200.0,\n  \"plannedDistance\": 50.5,\n  \"plannedDeparture\": \"2027-12-01T10:00:00\",\n  \"plannedArrival\": \"2027-12-01T14:00:00\",\n  \"remarks\": \"Fragile Cargo\"\n}"
            },
            "url": {
              "raw": "{{base_url}}/api/v1/trips",
              "host": ["{{base_url}}"],
              "path": ["api", "v1", "trips"]
            }
          },
          "response": []
        },
        {
          "name": "6. Create Trip Capacity Exceeded (Failure)",
          "event": [
            {
              "listen": "test",
              "script": {
                "exec": [
                  "pm.test(\"Status code is 400 Bad Request\", function () {",
                  "    pm.response.to.have.status(400);",
                  "});"
                ],
                "type": "text/javascript"
              }
            }
          ],
          "request": {
            "auth": {"type": "bearer", "bearer": [{"key": "token", "value": "{{jwt_token}}", "type": "string"}]},
            "method": "POST",
            "header": [{"key": "Content-Type", "value": "application/json"}],
            "body": {
              "mode": "raw",
              "raw": "{\n  \"source\": \"Warehouse A\",\n  \"destination\": \"Store C\",\n  \"vehicleId\": {{vehicle_id}},\n  \"driverId\": {{driver_id}},\n  \"cargoWeight\": 9999.0,\n  \"plannedDistance\": 10.5,\n  \"plannedDeparture\": \"2027-12-01T10:00:00\",\n  \"plannedArrival\": \"2027-12-01T14:00:00\"\n}"
            },
            "url": {
              "raw": "{{base_url}}/api/v1/trips",
              "host": ["{{base_url}}"],
              "path": ["api", "v1", "trips"]
            }
          },
          "response": []
        },
        {
          "name": "7. Dispatch Trip (Success)",
          "event": [
            {
              "listen": "test",
              "script": {
                "exec": [
                  "pm.test(\"Status code is 200\", function () {",
                  "    pm.response.to.have.status(200);",
                  "});",
                  "pm.test(\"Trip status is DISPATCHED\", function () {",
                  "    var jsonData = pm.response.json();",
                  "    pm.expect(jsonData.status).to.eql(\"DISPATCHED\");",
                  "});"
                ],
                "type": "text/javascript"
              }
            }
          ],
          "request": {
            "auth": {"type": "bearer", "bearer": [{"key": "token", "value": "{{jwt_token}}", "type": "string"}]},
            "method": "POST",
            "header": [],
            "url": {
              "raw": "{{base_url}}/api/v1/trips/{{trip_id}}/dispatch",
              "host": ["{{base_url}}"],
              "path": ["api", "v1", "trips", "{{trip_id}}", "dispatch"]
            }
          },
          "response": []
        },
        {
          "name": "8. Complete Trip (Success)",
          "event": [
            {
              "listen": "test",
              "script": {
                "exec": [
                  "pm.test(\"Status code is 200\", function () {",
                  "    pm.response.to.have.status(200);",
                  "});",
                  "pm.test(\"Trip status is COMPLETED\", function () {",
                  "    var jsonData = pm.response.json();",
                  "    pm.expect(jsonData.status).to.eql(\"COMPLETED\");",
                  "});"
                ],
                "type": "text/javascript"
              }
            }
          ],
          "request": {
            "auth": {"type": "bearer", "bearer": [{"key": "token", "value": "{{jwt_token}}", "type": "string"}]},
            "method": "POST",
            "header": [{"key": "Content-Type", "value": "application/json"}],
            "body": {
              "mode": "raw",
              "raw": "{\n  \"actualDistance\": 52.0,\n  \"fuelConsumed\": 15.5,\n  \"finalOdometer\": 12052.5,\n  \"remarks\": \"Traffic delayed arrival\"\n}"
            },
            "url": {
              "raw": "{{base_url}}/api/v1/trips/{{trip_id}}/complete",
              "host": ["{{base_url}}"],
              "path": ["api", "v1", "trips", "{{trip_id}}", "complete"]
            }
          },
          "response": []
        },
        {
          "name": "9. Get Trip By Id",
          "request": {
            "auth": {"type": "bearer", "bearer": [{"key": "token", "value": "{{jwt_token}}", "type": "string"}]},
            "method": "GET",
            "header": [],
            "url": {
              "raw": "{{base_url}}/api/v1/trips/{{trip_id}}",
              "host": ["{{base_url}}"],
              "path": ["api", "v1", "trips", "{{trip_id}}"]
            }
          },
          "response": []
        }
      ]
    }
  ],
  "event": [
    {
      "listen": "prerequest",
      "script": {
        "type": "text/javascript",
        "exec": [""]
      }
    },
    {
      "listen": "test",
      "script": {
        "type": "text/javascript",
        "exec": [""]
      }
    }
  ],
  "variable": [
    {
      "key": "base_url",
      "value": "http://localhost:8080",
      "type": "string"
    }
  ]
}
